groovindb/__init__.py
groovindb/cli.py
groovindb/types.py
groovindb/core/client.py
groovindb/core/client_gen.py
groovindb/core/config.py
groovindb/core/constants.py
groovindb/core/db.py
groovindb/core/models.py
groovindb/drivers/__init__.py
groovindb/drivers/base.py
groovindb/drivers/mysql.py
groovindb/drivers/postgresql.py
groovindb/drivers/sqlite.py
groovindb/utils/dsn.py
groovindb/utils/introspector.py
groovindb/utils/logger.py
groovindb/utils/validator.py
groovindb-1.1.1.data/data/CHANGELOG.md
groovindb-1.1.1.data/data/LICENSE
groovindb-1.1.1.data/data/README.md
groovindb-1.1.1.data/data/requirements.txt
groovindb-1.1.1.dist-info/LICENSE
groovindb-1.1.1.dist-info/METADATA
groovindb-1.1.1.dist-info/WHEEL
groovindb-1.1.1.dist-info/entry_points.txt
groovindb-1.1.1.dist-info/top_level.txt
groovindb-1.1.1.dist-info/RECORD
