Metadata-Version: 2.2
Name: groovindb
Version: 1.1.1
Summary: ORM asíncrono para Python con interfaz similar a Prisma
Home-page: https://bitbucket.org/groovinads/groovindb
Author: Juan Manuel Panozzo Zenere
Author-email: Juan Manuel Panozzo Zenere <jmpanozzoz@gmail.com>, Silvia Rus Mata <silvia.rus@groovinads.com>, Tomas Pinausig Castillo <tomas.pinausig@groovinads.com>
License: MIT
Project-URL: Homepage, https://bitbucket.org/groovinads/groovindb
Project-URL: Bug Tracker, https://bitbucket.org/groovinads/groovindb/issues
Project-URL: Documentation, https://bitbucket.org/groovinads/groovindb/src/master/README.md
Project-URL: Source Code, https://bitbucket.org/groovinads/groovindb
Keywords: database,orm,async,postgresql,mysql,prisma
Classifier: Development Status :: 4 - Beta
Classifier: Intended Audience :: Developers
Classifier: License :: OSI Approved :: MIT License
Classifier: Programming Language :: Python :: 3
Classifier: Programming Language :: Python :: 3.8
Classifier: Programming Language :: Python :: 3.9
Classifier: Programming Language :: Python :: 3.10
Classifier: Programming Language :: Python :: 3.11
Classifier: Operating System :: OS Independent
Classifier: Topic :: Database
Classifier: Topic :: Software Development :: Libraries :: Python Modules
Classifier: Framework :: AsyncIO
Requires-Python: >=3.8
License-File: LICENSE
Requires-Dist: click>=8.0.0
Requires-Dist: questionary>=1.10.0
Requires-Dist: asyncpg>=0.27.0
Requires-Dist: aiomysql>=0.1.1
Requires-Dist: colorama>=0.4.4
Requires-Dist: setuptools>=42.0.0
Requires-Dist: wheel>=0.37.0
Requires-Dist: redis>=5.0.0
Requires-Dist: psutil>=5.9.0
Requires-Dist: aiosqlite>=0.21.0
Dynamic: author
Dynamic: home-page
Dynamic: requires-python
